{
  "dataList": [
    {
      "id": 0,
      "place": "약지의 복도",
      "model": "호엔하임2",
      "content": "……."
    },
    {
      "id": 1,
      "model": "각성싱클레어1",
      "content": "하하… 이런 힘이 있으면 진작 말해줬어야지… 라는 표정이네요."
    },
    {
      "id": 2,
      "model": "각성싱클레어1",
      "content": "하지만 그런 편리한 방식이 아니라는 건, 호엔하임 씨라면 잘 아실 거예요."
    },
    {
      "id": 3,
      "model": "각성싱클레어1",
      "content": "따지자면… 지금 제일 놀란 건 저일 테죠. 저도 느닷없이 끌려오는 이 힘에 대해 몰랐고, 불려질 걸 예상치 못했으니."
    },
    {
      "id": 4,
      "model": "호엔하임2",
      "content": "그… 큼큼, 목이 졸리는 바람에… 목소리가 볼썽사납게 나오는군."
    },
    {
      "id": 5,
      "model": "호엔하임2",
      "content": "부하를 둘이나 잃을 처지에 놓인 마당에 죽을 고비가 찾아오니까 나도 모르게 살려고 발버둥을 치게 되더군. 웃긴 노릇이지."
    },
    {
      "id": 6,
      "model": "각성싱클레어1",
      "content": "안심하세요, 저분은 어떤 형태로든지 이겨내서 삶을 이어 나갈 거예요. 당신의, 우리의 생각보다 억센 분이시거든요."
    },
    {
      "id": 7,
      "model": "호엔하임2",
      "content": "…그런가, 다행이군."
    },
    {
      "id": 8,
      "model": "호엔하임2",
      "content": "……."
    },
    {
      "id": 9,
      "model": "호엔하임2",
      "content": "몇 년 후에서 온 건가?"
    },
    {
      "id": 10,
      "model": "각성싱클레어1",
      "content": "그건 말할 수가 없어요."
    },
    {
      "id": 11,
      "model": "호엔하임2",
      "content": "…불행히도 그리 낙관적인 미래로 보이진 않는데."
    },
    {
      "id": 12,
      "model": "각성싱클레어1",
      "content": "여기서 보면 과거도 그리 낙관적이진 않아요."
    },
    {
      "id": 13,
      "model": "각성싱클레어1",
      "content": "비록 1차 연기전쟁이라는 단어가 생길 줄 이때는 상상도 못 했었지만."
    },
    {
      "id": 14,
      "model": "이스마엘다침",
      "content": "저…"
    },
    {
      "id": 15,
      "model": "이스마엘다침",
      "content": "어떻게 된… 건가요? 파우스트 씨 당신 눈에도 보여요? 제가 피를 많이 흘려서 환각을 보고 있는 건지…"
    },
    {
      "id": 16,
      "model": "파우스트다침",
      "content": "…네."
    },
    {
      "id": 17,
      "model": "파우스트다침",
      "content": "…표지가… 당신을 부른 거군요."
    },
    {
      "id": 18,
      "model": "각성싱클레어1",
      "content": "표지는 매개체였을 뿐, 부른 주체는 결국 저예요."
    },
    {
      "id": 19,
      "model": "각성싱클레어1",
      "content": "동시에 발현되고 소환되어 버린 거죠."
    },
    {
      "id": 20,
      "model": "파우스트다침",
      "content": "그렇다면 혹시…"
    },
    {
      "id": 21,
      "model": "각성싱클레어1",
      "content": "아… 모든 표지가 이런 능력을 가지고 있는 건 아니에요. 제 표지가 이런 힘을 가진 거죠."
    },
    {
      "id": 22,
      "model": "이스마엘다침",
      "content": "그러니까… 당신… 미래에서 왔다고요? 거울세계가 아니고요…? 그, 그럼 원래 싱클레어 씨는요?"
    },
    {
      "id": 23,
      "model": "각성싱클레어1",
      "content": "원래라는 건 없어요. 이건 거울세계의 방식과는 다른… 갈라진 줄기에 가까우니까요."
    },
    {
      "id": 24,
      "model": "이스마엘다침",
      "content": "잠깐만요, 그러니까…"
    },
    {
      "id": 25,
      "model": "이스마엘다침",
      "content": "반드시 오는 건가요? 당신이 겪고 있는 그… 미래가…"
    },
    {
      "id": 26,
      "model": "각성싱클레어1",
      "content": "모르겠네요. 하지만 그럴지도요."
    },
    {
      "id": 27,
      "model": "각성싱클레어1",
      "content": "그렇게 비참하진 않아요."
    },
    {
      "id": 28,
      "model": "각성싱클레어1",
      "content": "어떻게든 살아지니까요."
    },
    {
      "id": 29,
      "model": "이스마엘다침",
      "content": "맞닥뜨릴 수밖에… 없는 건가요?"
    },
    {
      "id": 30,
      "model": "각성싱클레어1",
      "content": "……."
    },
    {
      "id": 31,
      "model": "각성싱클레어1",
      "content": "제가 불려 오기까지 겪었던 그 일상이… 여러분에게도 이어질지 혹은 피해 갈지는 모르겠어요."
    },
    {
      "id": 32,
      "model": "파우스트다침",
      "content": "…그래도 불가능하지는 않겠죠."
    },
    {
      "id": 33,
      "model": "각성싱클레어1",
      "content": "네, 힘든 길이 될 거예요. 아주, 많이."
    },
    {
      "id": 34,
      "model": "각성싱클레어1",
      "content": "지금은 이런 생각도 들어요."
    },
    {
      "id": 35,
      "model": "각성싱클레어1",
      "content": "어쩌면… 제가 걸어온 여정과 싸워온 전쟁터 속의 모든 경험은… 이 세계로 불러와지기 위해 만들어진 곁가지 세계 속의 일은 아니었을까."
    },
    {
      "id": 36,
      "model": "호엔하임2",
      "content": "모든 것은 이제 추측의 영역일 뿐이지."
    },
    {
      "id": 37,
      "model": "각성싱클레어1",
      "content": "맞아요. 그래도 제게 힘이 될 수 있다면 받아들이는 게 낫겠죠."
    },
    {
      "id": 38,
      "model": "각성싱클레어1",
      "content": "아쉽네요, 다른 분들도 전부 볼 수 있다면 좋았을 텐데. 다시 한번 보고 싶었던 얼굴도 있었고."
    },
    {
      "id": 39,
      "model": "각성싱클레어1",
      "content": "종종 떠올라요. 버스에서의 그 나날들이."
    },
    {
      "id": 40,
      "model": "각성싱클레어1",
      "content": "그리고 여기서는 그것만이… 지금 제 나날들을 지탱해 주는 것 같아요."
    },
    {
      "id": 41,
      "model": "이스마엘다침",
      "content": "……."
    },
    {
      "id": 42,
      "model": "각성싱클레어1",
      "content": "이제 떠나야겠어요. 더 그리워지기 전에."
    },
    {
      "id": 43,
      "model": "각성싱클레어1",
      "content": "떠나서 원래 있던 곳으로 돌아갈 줄 알았는데 이걸로 저는 죽는 것처럼 사라질 수도 있겠죠. 제가 그렇게 죽었는지 아닌지는 여러분도 저도 모르겠지만."
    },
    {
      "id": 44,
      "model": "각성싱클레어1",
      "content": "설령 제 존재가… 존재의 의미가 이걸로 끝이더라도."
    },
    {
      "id": 45,
      "model": "각성싱클레어1",
      "content": "죽어가는 동료들의 얼굴 대신, 반가운… 그리웠던 얼굴들을 봤으니 만족해요."
    },
    {
      "id": 46,
      "model": "각성싱클레어1",
      "content": "아, 파우스트 씨."
    },
    {
      "id": 47,
      "model": "각성싱클레어1",
      "content": "모든 것을 한 번에 다 슬퍼하지는 마세요."
    },
    {
      "id": 48,
      "model": "각성싱클레어1",
      "content": "그것만이 제가 드릴 수 있는 조언이에요."
    },
    {
      "id": 49,
      "model": "파우스트다침",
      "content": "……."
    },
    {
      "id": 50,
      "model": "호엔하임2",
      "content": "또 보자는 말은 의미 없겠지."
    },
    {
      "id": 51,
      "model": "각성싱클레어1",
      "content": "제 표지가 다시 빛나더라도 아마 지금의 제가 똑같이 온다는 보장은…"
    },
    {
      "id": 52,
      "model": "호엔하임2",
      "content": "없겠지."
    },
    {
      "id": 53,
      "model": "호엔하임2",
      "content": "그래도 뭐… 내 눈엔 많이 변하진 않은 것 같네만."
    },
    {
      "id": 54,
      "model": "호엔하임2",
      "content": "아, 적어도 키는 조금 더 큰 것 같군."
    },
    {
      "id": 55,
      "model": "각성싱클레어1",
      "content": "그런가요."
    },
    {
      "id": 56,
      "model": "호엔하임2",
      "content": "고맙네. 그리고 고생했네."
    },
    {
      "id": 57
    }
  ]
}