{
  "dataList": [
    {
      "id": "mirrordungeon_product_list",
      "content": "상품 목록"
    },
    {
      "id": "ego_gift_list",
      "content": "보유 E.G.O 기프트"
    },
    {
      "id": "normal_difficulty",
      "content": "일반 난이도"
    },
    {
      "id": "hard_difficulty",
      "content": "어려움 난이도"
    },
    {
      "id": "start_buffs",
      "content": "적용 효과 목록"
    },
    {
      "id": "enter_normal_difficulty",
      "content": "일반 난이도 입장"
    },
    {
      "id": "enter_hard_difficulty",
      "content": "어려움 난이도 입장"
    },
    {
      "id": "list_of_applied_effects",
      "content": "적용 효과 목록"
    },
    {
      "id": "activation_complete",
      "content": "활성화 완료"
    },
    {
      "id": "lack_of_points",
      "content": "별빛이 부족합니다."
    },
    {
      "id": "require_to_activate_former_buffs",
      "content": "이전 단계 버프를\n별새김해야 합니다."
    },
    {
      "id": "weekly_bonus_reward",
      "content": "주간 추가 보상"
    },
    {
      "id": "hard_dungeon_reward",
      "content": "어려움 난이도 보상"
    },
    {
      "id": "dungeon_shop_return_title",
      "content": "구매하지 않는다."
    },
    {
      "id": "dungeon_shop_return_desc",
      "content": "상점 화면으로 이동"
    },
    {
      "id": "dungeon_shop_heal_title_one",
      "content": "값비싼 자양강장제를 선택한다."
    },
    {
      "id": "dungeon_shop_heal_desc_one_hp_perc_mp_int",
      "content": "선택한 수감자 체력 {0}%, 정신력 {1} 회복"
    },
    {
      "id": "dungeon_shop_heal_title_all",
      "content": "에너지 드링크를 선택한다."
    },
    {
      "id": "dungeon_shop_heal_desc_all_hp_perc_mp_int",
      "content": "모든 수감자 체력 {0}%, 정신력 {1} 회복"
    },
    {
      "id": "dungeon_shop_purchase_title",
      "content": "구매한다."
    },
    {
      "id": "dungeon_shop_change_formation_title",
      "content": "부스러기 안에 보이는 거울 조각을 집어든다."
    },
    {
      "id": "dungeon_shop_change_formation_desc",
      "content": "현재 편성에 새로운 인격 또는 E.G.O를 추가"
    },
    {
      "id": "dungeon_shop_heal_character",
      "content": "수감자 회복"
    },
    {
      "id": "dungeon_shop_change_formation",
      "content": "편성"
    },
    {
      "id": "dungeon_shop_upgrade_personality",
      "content": "{0} 스킬 교체"
    },
    {
      "id": "dungeon_shop_upgrade_personality_0_title",
      "content": "적당한 비용을 치룬다."
    },
    {
      "id": "dungeon_shop_upgrade_personality_1_title",
      "content": "큰 값을 치룬다."
    },
    {
      "id": "dungeon_shop_upgrade_personality_2_title",
      "content": "어마어마한 값을 치룬다."
    },
    {
      "id": "dungeon_shop_upgrade_personality_desc",
      "content": "해당 인격이 보유한 [스킬 {2} - {0}] 중 하나를 [스킬 {3} - {1}]으로 변경"
    },
    {
      "id": "dungeon_shop_out",
      "content": "나가기"
    },
    {
      "id": "mirrordungeon_2_hard_open_at",
      "content": "거울의 거울 보통 난이도 클리어 시 개방"
    },
    {
      "id": "mirrordungeon_with_number",
      "content": "거울 던전 {0}"
    },
    {
      "id": "mirrordungeon_select_buffs_title",
      "content": "선택지 효과 선택"
    },
    {
      "id": "acquire_additional_rewards",
      "content": "추가 보상 받기"
    },
    {
      "id": "mirrordungeon_acquire_rewards_using_chance_desc",
      "content": "「주간 추가 보상」 기회를 소모하여 보너스 보상을 수령하시겠습니까?"
    },
    {
      "id": "mirrordungeon_acquire_rewards_not_using_chance_desc",
      "content": "「주간 추가 보상」 기회가 남아있습니다. \"주간 추가 보상\" 기회를 사용하지 않고 보상을 수령하시겠습니까?"
    },
    {
      "id": "mirrordungeon_acquire_rewards_no_chance_desc",
      "content": "보상을 수령하시겠습니까?"
    },
    {
      "id": "mirror_dungeon_start_buffs_chip_name",
      "content": "별빛"
    },
    {
      "id": "mirror_dungeon_exit_without_acquire_rewards",
      "content": "보상을 수령하지 않고 탐사를 종료하시겠습니까?"
    },
    {
      "id": "mirror_dungeon_buffs_title_1",
      "content": "반걸음 더"
    },
    {
      "id": "mirror_dungeon_buffs_title_2",
      "content": "투지"
    },
    {
      "id": "mirror_dungeon_buffs_title_3",
      "content": "약점 파악"
    },
    {
      "id": "mirror_dungeon_buffs_title_4",
      "content": "나아갈 투지"
    },
    {
      "id": "mirror_dungeon_buffs_title_5",
      "content": "약점 집중"
    },
    {
      "id": "mirror_dungeon_buffs_title_6",
      "content": "체력 단련"
    },
    {
      "id": "mirror_dungeon_buffs_title_7",
      "content": "엿보이는 간절함"
    },
    {
      "id": "mirror_dungeon_buffs_title_8",
      "content": "고강도 체력 단련"
    },
    {
      "id": "mirror_dungeon_buffs_title_9",
      "content": "자생"
    },
    {
      "id": "mirror_dungeon_buffs_title_10",
      "content": "맞물린 가능성"
    },
    {
      "id": "mirror_dungeon_buffs_title_11",
      "content": "단 하나의 주머니"
    },
    {
      "id": "mirror_dungeon_buffs_title_12",
      "content": "한걸음 더"
    },
    {
      "id": "mirror_dungeon_buffs_title_13",
      "content": "우연한 습득물"
    },
    {
      "id": "mirror_dungeon_buffs_title_14",
      "content": "돋보이는 주머니"
    },
    {
      "id": "mirror_dungeon_buffs_title_15",
      "content": "견고한 수비"
    },
    {
      "id": "mirror_dungeon_buffs_title_16",
      "content": "재빠른 다리"
    },
    {
      "id": "mirror_dungeon_buffs_title_17",
      "content": "준족"
    },
    {
      "id": "mirror_dungeon_buffs_title_18",
      "content": "스쳐가는 공격"
    },
    {
      "id": "mirror_dungeon_buffs_title_19",
      "content": "굳센 정신"
    },
    {
      "id": "mirrordungeon_unable_to_purchase_buffs_when_running_dungeon",
      "content": "던전 진행 중에는 시작 버프를 구매할 수 없습니다."
    },
    {
      "id": "mirrordungeon_resting_open",
      "content": "부디 편히 쉬었다 가시길!\n\n혹여 원하는 게 만남이라면, 책상 위에 그것을 올려주세요.\n\n- 자판기를 찾아 미로를 여행하는 편의점 주인 올림"
    },
    {
      "id": "mirrordungeon_shop_open",
      "content": "자판기에서 흘러나오는 진동음이 공간을 가득 메운다.\n\n그것은 우리가 무엇을 원하는지 알고 있다.\n\n우리 역시 그게 원하는 것이 무엇인지를 알고 있다."
    },
    {
      "id": "mirrordungeon_resting_heal_title",
      "content": "편히 쉰다."
    },
    {
      "id": "mirrordungeon_resting_heal_desc",
      "content": "수감자 회복"
    },
    {
      "id": "mirrordungeon_resting_heal_desc_1",
      "content": "선택한 수감자 체력 {0}% 회복"
    },
    {
      "id": "mirrordungeon_resting_heal_desc_2",
      "content": "모든 수감자 체력 {0}% 회복"
    },
    {
      "id": "mirrordungeon_resting_change_formation_title",
      "content": "부스러기를 테이블 위에 올려둔다."
    },
    {
      "id": "mirrordungeon_resting_change_formation_desc",
      "content": "현재 편성에 새로운 인격 또는 E.G.O를 추가"
    },
    {
      "id": "hard_difficulty_en",
      "content": "어려움 난이도"
    },
    {
      "id": "mirrordungeon_2_normal_open_at",
      "content": "주요이야기 4-54, 시작의 거울 클리어 시 개방"
    },
    {
      "id": "mirrordungeon_2_shop_stageinfo_title",
      "content": "진동음이 굵게 울리는 공간"
    },
    {
      "id": "mirrordungeon_2_shop_stageinfo_desc",
      "content": "섬뜩하리만치 텅 빈 공간이 자판기에서 흘러나오는 진동음으로 메워진다.\n\n그 목소리는 말한다. 너희가 가진 그 부스러기를 바친다면 쓸모있는 것으로 바꾸어 주겠다고.\n\n정체를 알 수 없는 그것을 향해 홀린 듯이 다가간다."
    },
    {
      "id": "mirrordungeon_2_resting_stageinfo_title",
      "content": "고요함이 짙게 드리운 공간"
    },
    {
      "id": "mirrordungeon_2_resting_stageinfo_desc",
      "content": "고요함에 고통을 묻어두거나,\n그 속에서 고통을 함께할 자를 꺼내어보자."
    },
    {
      "id": "dungeon_resting_change_formation_title",
      "content": "부스러기 안에 보이는 거울 조각을 집어든다."
    },
    {
      "id": "dungeon_resting_change_formation_desc",
      "content": "현재 편성에 새로운 인격 또는 E.G.O를 추가"
    },
    {
      "id": "dungeon_resting_heal_title_one",
      "content": "제일 피곤해보이는 수감자를 의자에 눕힌다."
    },
    {
      "id": "dungeon_resting_heal_title_all",
      "content": "수감자 전원이 의자에 걸터앉아 휴식을 취한다."
    },
    {
      "id": "ego_gift_info",
      "content": "E.G.O 기프트 정보"
    },
    {
      "id": "mirrordungeon_shop_gift_entrance",
      "content": "기이하고 신비로운 것에 자꾸만 시선이 간다."
    },
    {
      "id": "mirrordungeon_shop_gift_purchase",
      "content": "철컹거리며 무언가가 떨어지는 소리가 들린다."
    },
    {
      "id": "mirrordungeon_reenter",
      "content": "더 살 게 있을까?"
    },
    {
      "id": "mirrordungeon_shop_heal_one_who",
      "content": "안타깝게도 이 귀한 피로회복제는 하나 뿐이다.\n누가 마시는 게 좋을까?"
    },
    {
      "id": "mirrordungeon_shop_heal_one_answer",
      "content": "비싼 물건은 그 값을 하나보다.\n자양강장제를 맛본 수감자의 얼굴에는 피로는 커녕 광채가 어른거린다."
    },
    {
      "id": "mirrordungeon_shop_heal_all_answer",
      "content": "수감자 수만큼 에너지 드링크를 뽑았다.\n달고 시큼한 것을 맛보며, 모두의 얼굴에 이제야 피로가 좀 풀리는 모습이다."
    },
    {
      "id": "mirrordungeon_resting_heal_one_answer",
      "content": "잠시 누워 눈을 붙이도록 했다.\n휴식 시간이 끝날 무렵에 다시 보니 다행히 기운을 차린 듯한 모습이다."
    },
    {
      "id": "mirrordungeon_resting_heal_all_answer",
      "content": "모두 앉으려니 조금 비좁기는 했지만,\n모처럼 단비 같은 휴식이었다."
    },
    {
      "id": "mirrordungeon_shop_heal_one_after",
      "content": "모두 앉으려니 조금 비좁기는 했지만,\n모처럼 단비 같은 휴식이었다."
    },
    {
      "id": "mirrordungeon_shop_heal_one_who_right",
      "content": "피곤해 보이는 수감자를 선택한다."
    },
    {
      "id": "mirrordungeon_shop_upgrade_start_left",
      "content": "이 자판기 안에는 무한한 가능성이라는 개념이 실재하는 것일까."
    },
    {
      "id": "dungeon_encounter_guide_mirror_shop",
      "content": "상점"
    },
    {
      "id": "dungeon_encounter_guide_mirror_select_event",
      "content": "쉼터"
    },
    {
      "id": "dungeon_explore_floor",
      "content": "{0}층 탐사 중"
    },
    {
      "id": "lack_of_point_for_shop",
      "content": "코스트 부족"
    },
    {
      "id": "mirrordungeon_select_less_character_at_start",
      "content": "선택가능한 수감자 수보다 적게 편성되었습니다.\n이대로 진행하시겠습니까?"
    },
    {
      "id": "list_of_applied_effects_is_empty",
      "content": "현재 적용된 효과가 없습니다."
    },
    {
      "id": "give_up_rewards",
      "content": "수령 포기"
    },
    {
      "id": "mirror_dungeon_rewards_back_to_lobby_button",
      "content": "유리창으로 이동"
    },
    {
      "id": "mirror_dungeon_rewards_back_to_lobby_desc",
      "content": "유리창으로 이동하시겠습니까?\n탐사 종료 보상 창은 이후 거울 던전에 다시 입장할 때 재등장합니다."
    },
    {
      "id": "mirror_dungeon_rewards_back_to_lobby_button_lobby",
      "content": "목록으로 이동"
    },
    {
      "id": "mirrordungeon_resting_heal_one_who",
      "content": "자리가 그다지 넓진 않다.\n누구를 쉬게 하는 게 좋을까?"
    },
    {
      "id": "mirrordungeon_resting_heal_one_who_right",
      "content": "피곤해 보이는 수감자를 선택한다."
    },
    {
      "id": "mirror_dungeon_change_formation_release_character",
      "content": "선택 항목 일괄 취소"
    },
    {
      "id": "mirrordungeon_exit_shop",
      "content": "상점에서 나가시겠습니까?"
    },
    {
      "id": "mirrordungeon_exit_resting",
      "content": "쉼터에서 나가시겠습니까?"
    },
    {
      "id": "mirrordungeon_change_formation_confirm_less_participants",
      "content": "선택 횟수가 남았습니다.\n이대로 편성하시겠습니까?"
    },
    {
      "id": "mirrordungeon_change_formation_confirm_exact_participants",
      "content": "코스트를 사용하여 선택한 인격과 E.G.O를 편성하시겠습니까?"
    },
    {
      "id": "mirror_dungeon_clear_battle_reward_label",
      "content": "클리어 보상"
    },
    {
      "id": "mirror_dungeon_start_change_formation_but_button",
      "content": "구매"
    },
    {
      "id": "mirror_dungeon_give_up_ego_gift",
      "content": "선택하지 않음"
    },
    {
      "id": "mirror_dungeon_give_up_ego_gift_ask",
      "content": "E.G.O 기프트를 선택하지 않고 진행하시겠습니까?"
    },
    {
      "id": "mirror_dungeon_challenge_mode_description",
      "content": "도전 모드를 활성화할 경우, 무작위 편성이 진행됩니다.\n조합된 편성은 해당 편성으로 보상을 수령하기 전까지 변경되지 않습니다.\n도전 모드 상태로 클리어 시, 보상이 증가합니다."
    },
    {
      "id": "mirror_dungeon_challenge_mode_ask",
      "content": "도전 모드를 활성화하시겠습니까?"
    },
    {
      "id": "mirror_dungeon_challenge_mode",
      "content": "도전 모드"
    },
    {
      "id": "mirror_dungeon_hard_require_condition_title",
      "content": "권장 조건"
    },
    {
      "id": "mirror_dungeon_hard_require_condition_level",
      "content": "- 인격 레벨 40"
    },
    {
      "id": "mirror_dungeon_hard_require_condition_ego_gacksung",
      "content": "- E.G.O 환상 해석 3 단계"
    },
    {
      "id": "mirror_dungeon_hard_require_condition_personality_gacksung",
      "content": "- 인격 동기화 3 단계"
    },
    {
      "id": "mirror_dungeon_hard_require_condition_start_buf",
      "content": "- 시작 버프 전체 활성화"
    },
    {
      "id": "mirrordungeon_acquire_rewards_using_hard_using_chance_desc",
      "content": "남은 <color=#a16a3b>주간 추가 보상</color>과 <color=#ff0000>어려움 난이도 보상</color>을 전부 소모하여 보상을 수령하시겠습니까?"
    },
    {
      "id": "mirrordungeon_acquire_rewards_using_hard_not_using_chance_desc",
      "content": "사용 가능한 <color=#a16a3b>주간 추가 보상</color>이 있습니다.\n\n<color=#ff0000>어려움 난이도 보상</color>만 소모하여 보상을 수령하시겠습니까?"
    },
    {
      "id": "mirrordungeon_acquire_rewards_using_hard_no_chance_desc",
      "content": " <color=#ff0000>어려움 난이도 보상</color>을 소모하여 보상을 수령하시겠습니까?"
    },
    {
      "id": "mirrordungeon_acquire_rewards_not_using_hard_chance_using_chance_desc",
      "content": "사용 가능한 <color=#ff0000>어려움 난이도 보상</color>이 있습니다.\n\n<color=#a16a3b>주간 추가 보상</color>만 소모하여 보상을 수령하시겠습니까?"
    },
    {
      "id": "mirrordungeon_acquire_rewards_not_using_hard_chance_not_using_chance_desc",
      "content": "사용 가능한 <color=#a16a3b>주간 추가 보상</color>과 <color=#ff0000>어려움 난이도 보상</color>이 있습니다.\n\n이를 소모하지 않고 보상을 수령하시겠습니까?"
    },
    {
      "id": "mirrordungeon_acquire_rewards_not_using_hard_chance_no_chance_desc",
      "content": "사용 가능한 <color=#ff0000>어려움 난이도 보상</color>이 있습니다.\n\n이를 소모하지 않고 보상을 수령하시겠습니까?"
    },
    {
      "id": "mirrordungeon_acquire_rewards_no_hard_chance_using_chance_desc",
      "content": "<color=#a16a3b>주간 추가 보상</color>을 소모하여 보상을 수령하시겠습니까?"
    },
    {
      "id": "mirrordungeon_acquire_rewards_no_hard_chance_not_using_chance_desc",
      "content": "사용 가능한 <color=#a16a3b>주간 추가 보상</color>이 있습니다.\n\n이를 소모하지 않고 보상을 수령하시겠습니까?"
    },
    {
      "id": "mirrordungeon_acquire_rewards_no_hard_chance_no_chance_desc",
      "content": "보상을 수령하시겠습니까?"
    },
    {
      "id": "mirrordungeon_hard_no_reward_desc",
      "content": "<color=#ff0000>해당 콘텐츠 보상을 이미 획득하여, 보상을 획득할 수 없습니다.</color>"
    },
    {
      "id": "mirror_dungeon_3_buffs_title_1",
      "content": "여정의 시작"
    },
    {
      "id": "mirror_dungeon_3_buffs_title_2",
      "content": "기회 잡기"
    },
    {
      "id": "mirror_dungeon_3_buffs_title_3",
      "content": "유비무환"
    },
    {
      "id": "mirror_dungeon_3_buffs_title_4",
      "content": "노력의 산물"
    },
    {
      "id": "mirror_dungeon_3_buffs_title_5",
      "content": "값진 결실"
    },
    {
      "id": "mirror_dungeon_3_buffs_title_6",
      "content": "새로운 발견"
    },
    {
      "id": "mirror_dungeon_3_buffs_title_7",
      "content": "전리품"
    },
    {
      "id": "mirror_dungeon_3_buffs_title_8",
      "content": "다다익선"
    },
    {
      "id": "mirror_dungeon_3_buffs_title_9",
      "content": "다져진 신뢰"
    },
    {
      "id": "mirror_dungeon_3_buffs_title_10",
      "content": "절차탁마"
    },
    {
      "id": "mirror_dungeon_3_buffs_title_11",
      "content": "이름값"
    },
    {
      "id": "mirror_dungeon_3_buffs_title_12",
      "content": "명성과 위업"
    },
    {
      "id": "mirror_dungeon_3_buffs_title_13",
      "content": "권리"
    },
    {
      "id": "mirror_dungeon_3_buffs_title_14",
      "content": "금의환향"
    },
    {
      "id": "mirror_dungeon_3_buffs_title_15",
      "content": "목표"
    },
    {
      "id": "mirror_dungeon_3_buffs_title_16",
      "content": "준비성"
    },
    {
      "id": "mirror_dungeon_3_buffs_title_17",
      "content": "나아갈 투지"
    },
    {
      "id": "mirror_dungeon_3_buffs_title_18",
      "content": "체력 단련"
    },
    {
      "id": "md3_buffs_summaryDesc_101",
      "content": "3등급 기프트 등장"
    },
    {
      "id": "md3_buffs_summaryDesc_1011",
      "content": "화상 기프트 출현 등급 상승"
    },
    {
      "id": "md3_buffs_summaryDesc_1012",
      "content": "출혈 기프트 출현 등급 상승"
    },
    {
      "id": "md3_buffs_summaryDesc_1013",
      "content": "진동 기프트 출현 등급 상승"
    },
    {
      "id": "md3_buffs_summaryDesc_1014",
      "content": "파열 기프트 출현 등급 상승"
    },
    {
      "id": "md3_buffs_summaryDesc_1015",
      "content": "침잠 기프트 출현 등급 상승"
    },
    {
      "id": "md3_buffs_summaryDesc_1016",
      "content": "호흡 기프트 출현 등급 상승"
    },
    {
      "id": "md3_buffs_summaryDesc_1017",
      "content": "충전 기프트 출현 등급 상승"
    },
    {
      "id": "md3_buffs_summaryDesc_1018",
      "content": "무작위 기프트 출현 등급 상승"
    },
    {
      "id": "md3_buffs_summaryDesc_102",
      "content": "4등급 이상 기프트 등장 및 기프트 출현 등급 상승"
    },
    {
      "id": "md3_buffs_summaryDesc_1021",
      "content": "기프트 출현 등급 상승"
    },
    {
      "id": "md3_buffs_summaryDesc_1022",
      "content": "기프트 출현 등급 상승"
    },
    {
      "id": "md3_buffs_summaryDesc_1023",
      "content": "기프트 출현 등급 상승"
    },
    {
      "id": "md3_buffs_summaryDesc_103",
      "content": "등장하는 기프트 수 +1"
    },
    {
      "id": "md3_buffs_summaryDesc_1031",
      "content": "등장하는 기프트 수 +1"
    },
    {
      "id": "md3_buffs_summaryDesc_104",
      "content": "등장하는 기프트 수 +1"
    },
    {
      "id": "md3_buffs_summaryDesc_1041",
      "content": "등장하는 화상 기프트 수 +1"
    },
    {
      "id": "md3_buffs_summaryDesc_1042",
      "content": "등장하는 출혈 기프트 수 +1"
    },
    {
      "id": "md3_buffs_summaryDesc_1043",
      "content": "등장하는 진동 기프트 수 +1"
    },
    {
      "id": "md3_buffs_summaryDesc_1044",
      "content": "등장하는 파열 기프트 수 +1"
    },
    {
      "id": "md3_buffs_summaryDesc_1045",
      "content": "등장하는 침잠 기프트 수 +1"
    },
    {
      "id": "md3_buffs_summaryDesc_1046",
      "content": "등장하는 호흡 기프트 수 +1"
    },
    {
      "id": "md3_buffs_summaryDesc_1047",
      "content": "등장하는 충전 기프트 수 +1"
    },
    {
      "id": "md3_buffs_summaryDesc_1048",
      "content": "등장하는 무작위 기프트 수 +1"
    },
    {
      "id": "md3_buffs_summaryDesc_105",
      "content": "시작 코스트 50 획득"
    },
    {
      "id": "md3_buffs_summaryDesc_1051",
      "content": "시작 코스트 +50"
    },
    {
      "id": "md3_buffs_summaryDesc_1052",
      "content": "시작 코스트 +50"
    },
    {
      "id": "md3_buffs_summaryDesc_1053",
      "content": "시작 코스트 +50"
    },
    {
      "id": "md3_buffs_summaryDesc_106",
      "content": "기프트 3종 추가 등장"
    },
    {
      "id": "md3_buffs_summaryDesc_1061",
      "content": "화상 기프트 2종 추가 등장"
    },
    {
      "id": "md3_buffs_summaryDesc_1062",
      "content": "출혈 기프트 2종 추가 등장"
    },
    {
      "id": "md3_buffs_summaryDesc_1063",
      "content": "진동 기프트 2종 추가 등장"
    },
    {
      "id": "md3_buffs_summaryDesc_1064",
      "content": "파열 기프트 2종 추가 등장"
    },
    {
      "id": "md3_buffs_summaryDesc_1065",
      "content": "침잠 기프트 2종 추가 등장"
    },
    {
      "id": "md3_buffs_summaryDesc_1066",
      "content": "호흡 기프트 2종 추가 등장"
    },
    {
      "id": "md3_buffs_summaryDesc_1067",
      "content": "충전 기프트 2종 추가 등장"
    },
    {
      "id": "md3_buffs_summaryDesc_107",
      "content": "전투에서 획득하는 코스트 증가"
    },
    {
      "id": "md3_buffs_summaryDesc_1071",
      "content": "일반 전투에서 획득하는 코스트 증가"
    },
    {
      "id": "md3_buffs_summaryDesc_1072",
      "content": "집중 전투에서 획득하는 코스트 증가"
    },
    {
      "id": "md3_buffs_summaryDesc_1073",
      "content": "위험 전투에서 획득하는 코스트 증가"
    },
    {
      "id": "md3_buffs_summaryDesc_1074",
      "content": "층 보스 전투에서 획득하는 코스트 증가"
    },
    {
      "id": "md3_buffs_summaryDesc_108",
      "content": "기프트 선택 수 +1"
    },
    {
      "id": "md3_buffs_summaryDesc_109",
      "content": "새로고침 비용 감소"
    },
    {
      "id": "md3_buffs_summaryDesc_1091",
      "content": "새로고침 비용 감소"
    },
    {
      "id": "md3_buffs_summaryDesc_1092",
      "content": "낮은 확률로 새로 고침 비용 소모 없음"
    },
    {
      "id": "md3_buffs_summaryDesc_1093",
      "content": "스킬 교체 비용 감소"
    },
    {
      "id": "md3_buffs_summaryDesc_1094",
      "content": "스킬 교체 비용 감소"
    },
    {
      "id": "md3_buffs_summaryDesc_110",
      "content": "강화 비용 감소"
    },
    {
      "id": "md3_buffs_summaryDesc_1101",
      "content": "낮은 확률로 강화 비용 소모 없음"
    },
    {
      "id": "md3_buffs_summaryDesc_1102",
      "content": "화상 기프트 강화 비용 감소"
    },
    {
      "id": "md3_buffs_summaryDesc_1103",
      "content": "출혈 기프트 강화 비용 감소"
    },
    {
      "id": "md3_buffs_summaryDesc_1104",
      "content": "진동 기프트 강화 비용 감소"
    },
    {
      "id": "md3_buffs_summaryDesc_1105",
      "content": "파열 기프트 강화 비용 감소"
    },
    {
      "id": "md3_buffs_summaryDesc_1106",
      "content": "침잠 기프트 강화 비용 감소"
    },
    {
      "id": "md3_buffs_summaryDesc_1107",
      "content": "호흡 기프트 강화 비용 감소"
    },
    {
      "id": "md3_buffs_summaryDesc_1108",
      "content": "충전 기프트 강화 비용 감소"
    },
    {
      "id": "md3_buffs_summaryDesc_111",
      "content": "기프트 판매 비용 증가"
    },
    {
      "id": "md3_buffs_summaryDesc_1111",
      "content": "기프트 판매 비용 증가"
    },
    {
      "id": "md3_buffs_summaryDesc_112",
      "content": "기프트 구매 비용 감소"
    },
    {
      "id": "md3_buffs_summaryDesc_1121",
      "content": "화상 기프트 구매 비용 감소"
    },
    {
      "id": "md3_buffs_summaryDesc_1122",
      "content": "출혈 기프트 구매 비용 감소"
    },
    {
      "id": "md3_buffs_summaryDesc_1123",
      "content": "진동 기프트 구매 비용 감소"
    },
    {
      "id": "md3_buffs_summaryDesc_1124",
      "content": "파열 기프트 구매 비용 감소"
    },
    {
      "id": "md3_buffs_summaryDesc_1125",
      "content": "침잠 기프트 구매 비용 감소"
    },
    {
      "id": "md3_buffs_summaryDesc_1126",
      "content": "호흡 기프트 구매 비용 감소"
    },
    {
      "id": "md3_buffs_summaryDesc_1127",
      "content": "충전 기프트 구매 비용 감소"
    },
    {
      "id": "md3_buffs_summaryDesc_1128",
      "content": "범용 기프트 구매 비용 감소"
    },
    {
      "id": "md3_buffs_summaryDesc_151",
      "content": "E.G.O 기프트 선택 수 +1"
    },
    {
      "id": "md3_buffs_summaryDesc_152",
      "content": "시작 코스트 + 250"
    },
    {
      "id": "md3_buffs_summaryDesc_153",
      "content": "시작 단계에서 선택한 항목의 4등급 무작위 E.G.O 기프트를 추가로 획득"
    },
    {
      "id": "md3_buffs_summaryDesc_121",
      "content": "모든 속성 E.G.O 자원 +1"
    },
    {
      "id": "md3_buffs_summaryDesc_1211",
      "content": "모든 속성 E.G.O 자원 +1"
    },
    {
      "id": "md3_buffs_summaryDesc_1212",
      "content": "속도 최댓값 +1"
    },
    {
      "id": "md3_buffs_summaryDesc_1213",
      "content": "속도 최댓값 +1"
    },
    {
      "id": "md3_buffs_summaryDesc_122",
      "content": "가하는 피해량 3% 증가"
    },
    {
      "id": "md3_buffs_summaryDesc_1221",
      "content": "가하는 피해량 3% 증가"
    },
    {
      "id": "md3_buffs_summaryDesc_1222",
      "content": "공격 레벨 1 증가"
    },
    {
      "id": "md3_buffs_summaryDesc_1223",
      "content": "공격 레벨 1 증가"
    },
    {
      "id": "md3_buffs_summaryDesc_1224",
      "content": "가하는 참격 피해량 4% 증가"
    },
    {
      "id": "md3_buffs_summaryDesc_1225",
      "content": "가하는 관통 피해량 4% 증가"
    },
    {
      "id": "md3_buffs_summaryDesc_1226",
      "content": "가하는 타격 피해량 4% 증가"
    },
    {
      "id": "md3_buffs_summaryDesc_123",
      "content": "받는 피해량 3% 감소"
    },
    {
      "id": "md3_buffs_summaryDesc_1231",
      "content": "받는 피해량 3% 감소"
    },
    {
      "id": "md3_buffs_summaryDesc_1232",
      "content": "방어 레벨 1 증가"
    },
    {
      "id": "md3_buffs_summaryDesc_1233",
      "content": "방어 레벨 2 증가"
    },
    {
      "id": "md3_buffs_summaryDesc_1234",
      "content": "참격 내성 0.1만큼 감소"
    },
    {
      "id": "md3_buffs_summaryDesc_1235",
      "content": "관통 내성 0.1만큼 감소"
    },
    {
      "id": "md3_buffs_summaryDesc_1236",
      "content": "타격 내성 0.1만큼 감소"
    }
  ]
}