{
  "dataList": [
    {
      "id": 9001,
      "name": "炼狱蝶之梦",
      "desc": "通过技能效果使已带有烧伤 状态的敌人增加烧伤 强度时，使随机敌人增加共计3级烧伤 强度\n\n激活愤怒完全共鸣时，则在战斗开始时使随机敌人增加共计5级烧伤 强度。",
      "simpleDesc": [
        {
          "abilityID": 9001,
          "simpleDesc": "随机增加3级烧伤 强度"
        },
        {
          "abilityID": 90011,
          "simpleDesc": "随机增加5级烧伤 强度"
        }
      ]
    },
    {
      "id": 9002,
      "name": "倒错症",
      "desc": "通过技能击杀敌人时，获得1个该技能所对应的罪孽碎片\n\n若该技能为愤怒技能，则改为获得该人格所有技能对应的罪孽碎片各1个。",
      "simpleDesc": [
        {
          "abilityID": 9002,
          "simpleDesc": "获得1个技能所对应的罪孽碎片"
        },
        {
          "abilityID": 90021,
          "simpleDesc": "获得所有技能所对应的罪孽碎片各1个"
        }
      ]
    },
    {
      "id": 9003,
      "name": "尘归尘，土归土",
      "desc": "战斗开始时，若所有敌人（或所有异想体部位）都带有烧伤 ，则使所有敌人增加2级烧伤 强度。",
      "simpleDesc": [
        {
          "abilityID": 9003,
          "simpleDesc": "增加2级烧伤 强度"
        }
      ]
    },
    {
      "id": 9004,
      "name": "输血袋",
      "desc": "通过技能对敌人造成伤害时，恢复技能使用者已失去体力7.5%的体力（同一角色每回合至多触发1次）\n\n若该技能为愤怒技能，则恢复量改为15%。",
      "simpleDesc": [
        {
          "abilityID": 9004,
          "simpleDesc": "恢复已失去体力7.5%的体力"
        },
        {
          "abilityID": 90041,
          "simpleDesc": "恢复已失去体力15%的体力"
        }
      ]
    },
    {
      "id": 9005,
      "name": "伤口郭公虫",
      "desc": "使用愤怒技能或带有流血效果的技能造成伤害时，使目标增加3级流血 强度。",
      "simpleDesc": [
        {
          "abilityID": 9005,
          "simpleDesc": "增加3级流血 强度"
        }
      ]
    },
    {
      "id": 9006,
      "name": "咖啡与纸鹤",
      "desc": "回合开始时，获得1个罪孽碎片，其属性为上回合未使用罪孽属性中的随机一种。\n\n若上回合使用了色欲技能，则改为获得所有上回合未使用罪孽属性的碎片各1个。",
      "simpleDesc": [
        {
          "abilityID": 9006,
          "simpleDesc": "获得1个随机罪孽碎片"
        },
        {
          "abilityID": 90061,
          "simpleDesc": "获得所有罪孽碎片各1个"
        }
      ]
    },
    {
      "id": 9007,
      "name": "黯淡的绯红之蛾",
      "desc": "每一回合中第一次使用技能造成伤害时，对随机1个敌人造成伤害量50%的固定伤害\n\n若该技能为色欲技能，则会由1个敌人改为2个敌人",
      "simpleDesc": [
        {
          "abilityID": 9007,
          "simpleDesc": "造成固定伤害"
        },
        {
          "abilityID": 90071,
          "simpleDesc": "造成固定伤害"
        }
      ]
    },
    {
      "id": 9008,
      "name": "染血铁钉",
      "desc": "使用只有1个硬币的技能造成伤害后，施加1层流血与1层破绽。\n\n若目标处于流血状态，则会由1层流血改为3层流血",
      "simpleDesc": [
        {
          "abilityID": 9008,
          "simpleDesc": "施加1层流血与1层破绽"
        },
        {
          "abilityID": 90081,
          "simpleDesc": "施加3层流血与1层破绽"
        }
      ]
    },
    {
      "id": 9009,
      "name": "炽热的牺牲",
      "desc": "若使用色欲技能或拥有烧伤效果的技能造成伤害时，施加3层烧伤。\n\n回合开始时，若敌人的烧伤层数不低于20，则会使其烧伤层数翻倍",
      "simpleDesc": [
        {
          "abilityID": 9009,
          "simpleDesc": "施加3层烧伤"
        },
        {
          "abilityID": 90091,
          "simpleDesc": "烧伤层数翻倍"
        }
      ]
    },
    {
      "id": 9010,
      "name": "血腥装置",
      "desc": "回合开始时，对随机1位友方角色施加2层Damage Up。\n\n优先选取拥有色欲技能的友方角色；并且由2层改为3层",
      "simpleDesc": [
        {
          "abilityID": 9010,
          "simpleDesc": "施加2层Damage Up"
        },
        {
          "abilityID": 90101,
          "simpleDesc": "施加3层Damage Up"
        }
      ]
    },
    {
      "id": 9011,
      "name": "太阳雨",
      "desc": "当激活怠惰完全共鸣或使用能够攻击多个角色的技能时，\n\n战斗开始时将使所有友方角色技能威力+2",
      "simpleDesc": [
        {
          "abilityID": 9011,
          "simpleDesc": "技能威力+2"
        }
      ]
    },
    {
      "id": 9012,
      "name": "今日的神情",
      "desc": "使用怠惰技能或打击技能击杀敌人时，获得2层Blunt Power Up，持续2回合",
      "simpleDesc": [
        {
          "abilityID": 9012,
          "simpleDesc": "打击技能威力+2"
        }
      ]
    },
    {
      "id": 9013,
      "name": "一捆护身符",
      "desc": "使用单个技能造成至少12点伤害时，施加2层破裂\n\n若该技能为斩击技能，则会由2层改为4层",
      "simpleDesc": [
        {
          "abilityID": 9013,
          "simpleDesc": "施加2层破裂"
        },
        {
          "abilityID": 90131,
          "simpleDesc": "施加4层破裂"
        }
      ]
    },
    {
      "id": 9014,
      "name": "锈蚀的纪念币",
      "desc": "若友方角色在战斗阶段首次使用的只有1个硬币的技能没有击杀敌人，则会再次使用该技能\n\n使用怠惰技能或只有1个硬币的技能击杀敌人时，下一回合该角色技能威力+1",
      "simpleDesc": [
        {
          "abilityID": 9014,
          "simpleDesc": "再次使用技能"
        },
        {
          "abilityID": 90141,
          "simpleDesc": "技能威力+1"
        }
      ]
    },
    {
      "id": 9015,
      "name": "血与汗与泪",
      "desc": "使用技能对陷入混乱的敌人造成的伤害+10%\n\n若该技能为怠惰技能，则会由10%改为20%",
      "simpleDesc": [
        {
          "abilityID": 9015,
          "simpleDesc": "造成的伤害+10%"
        },
        {
          "abilityID": 90151,
          "simpleDesc": "造成的伤害+20%"
        }
      ]
    },
    {
      "id": 9016,
      "name": "绿色精神",
      "desc": "使用暴食技能对未陷入混乱的敌人造成伤害时，或通过技能效果施加震颤时，对随机1个敌人施加1层震颤，重复4次",
      "simpleDesc": [
        {
          "abilityID": 9016,
          "simpleDesc": "随机施加4层震颤"
        }
      ]
    },
    {
      "id": 9017,
      "name": "考古石碑",
      "desc": "每当敌人陷入混乱时，恢复体力最低的友方角色最大体力5%的体力\n\n若该友方角色有暴食技能，则会由5%改为10%",
      "simpleDesc": [
        {
          "abilityID": 9017,
          "simpleDesc": "恢复最大体力5%的体力"
        },
        {
          "abilityID": 90171,
          "simpleDesc": "恢复最大体力10%的体力"
        }
      ]
    },
    {
      "id": 9018,
      "name": "玫瑰王冠",
      "desc": "回合开始时，对随机1个敌人施加4层破裂\n\n若激活暴食完全共鸣，战斗开始时对所有敌人施加2层破裂",
      "simpleDesc": [
        {
          "abilityID": 9018,
          "simpleDesc": "施加4层破裂"
        },
        {
          "abilityID": 90181,
          "simpleDesc": "施加2层破裂"
        }
      ]
    },
    {
      "id": 9019,
      "name": "粘性树脂",
      "desc": "使用暴食技能或突刺技能造成伤害时，施加1层Defense Down",
      "simpleDesc": [
        {
          "abilityID": 9019,
          "simpleDesc": "施加1层Defense Down"
        }
      ]
    },
    {
      "id": 9020,
      "name": "棉花",
      "desc": "回合开始时，解除敌人的混乱状态，并对其施加(8 + 混乱等级 x 4)层流血，随后使其流血强度+2",
      "simpleDesc": [
        {
          "abilityID": 9020,
          "simpleDesc": "施加(8 + 混乱等级 x 4)层流血并使其流血强度+2"
        }
      ]
    },
    {
      "id": 9021,
      "name": "蓝色芝宝牌打火机",
      "desc": "回合开始时，获得1点忧郁E.G.O资源与1点随机其他2种E.G.O资源",
      "simpleDesc": [
        {
          "abilityID": 9021,
          "simpleDesc": "获得1点忧郁E.G.O资源与1点随机其他2种E.G.O资源"
        }
      ]
    },
    {
      "id": 9022,
      "name": "幻痛",
      "desc": "技能对单个目标造成的伤害+15%\n\n若激活忧郁完全共鸣，战斗开始时对所有友方角色施加1层Attack Up",
      "simpleDesc": [
        {
          "abilityID": 9022,
          "simpleDesc": "造成的伤害+15%"
        },
        {
          "abilityID": 90221,
          "simpleDesc": "施加1层Attack Up"
        }
      ]
    },
    {
      "id": 9023,
      "name": "雷霆树枝",
      "desc": "使用技能施加破裂时，施加的破裂层数+1，强度+1",
      "simpleDesc": [
        {
          "abilityID": 9023,
          "simpleDesc": "施加的破裂层数+1，强度+1"
        }
      ]
    },
    {
      "id": 9024,
      "name": "融化眼球",
      "desc": "敌人的震颤爆发时，对其施加3层Defense Down",
      "simpleDesc": [
        {
          "abilityID": 9024,
          "simpleDesc": "施加3层Defense Down"
        }
      ]
    },
    {
      "id": 9025,
      "name": "灰色大衣",
      "desc": "使用能够攻击多个角色的技能时，造成的伤害+20%\n\n使用忧郁技能或能够攻击多个角色的技能时造成伤害时，恢复伤害量20%的体力",
      "simpleDesc": [
        {
          "abilityID": 9025,
          "simpleDesc": "造成的伤害+20%"
        },
        {
          "abilityID": 90251,
          "simpleDesc": "恢复伤害量20%的体力"
        }
      ]
    },
    {
      "id": 9026,
      "name": "刺青：大器晚成",
      "desc": "使用傲慢技能或只有1个硬币的技能时，获得1层Attack Up与Defense Up",
      "simpleDesc": [
        {
          "abilityID": 9026,
          "simpleDesc": "获得1层Attack Up与Defense Up."
        }
      ]
    },
    {
      "id": 9027,
      "name": "谷底之星",
      "desc": "造成打击伤害时，追加5点神志伤害\n\n若该技能为傲慢技能，则会由5点改为8点",
      "simpleDesc": [
        {
          "abilityID": 9027,
          "simpleDesc": "追加5点神志伤害"
        },
        {
          "abilityID": 90271,
          "simpleDesc": "追加8点神志伤害"
        }
      ]
    },
    {
      "id": 9028,
      "name": "成见",
      "desc": "第三回合开始时，体力最低的友方角色恢复最大生命值15%的体力\n\n若激活傲慢完全共鸣，战斗开始时体力最低的友方角色恢复已损失体力10%的体力",
      "simpleDesc": [
        {
          "abilityID": 9028,
          "simpleDesc": "恢复最大生命值15%的体力"
        },
        {
          "abilityID": 90281,
          "simpleDesc": "恢复已损失体力10%的体力"
        }
      ]
    },
    {
      "id": 9029,
      "name": "又小又很淘气的普尔希",
      "desc": "若目标处于流血状态，造成的伤害+10%，受到的伤害-20%\n\n拥有傲慢技能的友方角色将由+10%/-20%改为+20%/-30%",
      "simpleDesc": [
        {
          "abilityID": 9029,
          "simpleDesc": "造成的伤害+10%，受到的伤害-20%"
        },
        {
          "abilityID": 90291,
          "simpleDesc": "造成的伤害+20%，受到的伤害-30%"
        }
      ]
    },
    {
      "id": 9030,
      "name": "收藏头骨",
      "desc": "使用傲慢技能或突刺技能击杀敌人时，获得2层Pierce Power Up，持续2回合",
      "simpleDesc": [
        {
          "abilityID": 9030,
          "simpleDesc": "突刺技能威力+2"
        }
      ]
    },
    {
      "id": 9031,
      "name": "辉光分歧",
      "desc": "战斗开始时，对所有敌人施加4层强度为4的震颤\n\n使用嫉妒技能造成伤害时，施加2层震颤",
      "simpleDesc": [
        {
          "abilityID": 9031,
          "simpleDesc": "施加4层震颤"
        },
        {
          "abilityID": 90311,
          "simpleDesc": "施加2层震颤"
        }
      ]
    },
    {
      "id": 9032,
      "name": "梦中的电子羊",
      "desc": "使用嫉妒技能或斩击技能击杀敌人时，获得2层Slash Power Up，持续2回合\n\n若激活嫉妒完全共鸣，战斗开始时对所有友方角色施加1层Attack Up与Defense Up",
      "simpleDesc": [
        {
          "abilityID": 9032,
          "simpleDesc": "斩击技能威力+2"
        },
        {
          "abilityID": 90321,
          "simpleDesc": "施加1层Attack Up与Defense Up"
        }
      ]
    },
    {
      "id": 9033,
      "name": "正常工作的电池",
      "desc": "使用技能造成伤害时，施加3层破裂\n\n若该技能为嫉妒技能，则会由3层改为5层",
      "simpleDesc": [
        {
          "abilityID": 9033,
          "simpleDesc": "Inflict 3 Rupture"
        },
        {
          "abilityID": 90331,
          "simpleDesc": "Inflict 5 Rupture"
        }
      ]
    },
    {
      "id": 9034,
      "name": "精确逻辑电路",
      "desc": "使用嫉妒技能或拥有烧伤效果的技能造成伤害时，施加（技能硬币总数/2）层烧伤（取整）",
      "simpleDesc": [
        {
          "abilityID": 9034,
          "simpleDesc": "施加（技能硬币总数/2）层烧伤"
        }
      ]
    },
    {
      "id": 9035,
      "name": "巫毒娃娃",
      "desc": "回合开始时，对所有敌人造成3点固定伤害\n\n对体力低于33%的敌人施加1层Attack Power Down",
      "simpleDesc": [
        {
          "abilityID": 9035,
          "simpleDesc": "造成3点固定伤害"
        },
        {
          "abilityID": 90351,
          "simpleDesc": "造成3点固定伤害并施加1层Attack Power Down"
        }
      ]
    },
    {
      "id": 9036,
      "name": "卡蜜拉",
      "desc": "战斗开始时，非异想体的敌人受到最大体力20%的固定伤害",
      "simpleDesc": [
        {
          "abilityID": 9036,
          "simpleDesc": "受到最大体力20%的固定伤害"
        }
      ]
    },
    {
      "id": 9037,
      "name": "瓶中婴儿",
      "desc": "战斗开始时，获得1点所有的E.G.O资源",
      "simpleDesc": [
        {
          "abilityID": 9037,
          "simpleDesc": "获得1点所有的E.G.O资源"
        }
      ]
    },
    {
      "id": 9038,
      "name": "软体动物猎人",
      "desc": "进入异想体战斗时，对所有友方角色施加2层Damage Up",
      "simpleDesc": [
        {
          "abilityID": 9038,
          "simpleDesc": "施加2层Damage Up"
        }
      ]
    },
    {
      "id": 9039,
      "name": "归乡",
      "desc": "进入战斗时，所有参战的角色恢复最大体力12%的体力",
      "simpleDesc": [
        {
          "abilityID": 9039,
          "simpleDesc": "恢复最大体力12%的体力"
        }
      ]
    },
    {
      "id": 9040,
      "name": "明日的命运",
      "desc": "选择E.G.O饰品时，获得1个额外的选项",
      "simpleDesc": [
        {
          "abilityID": 9040,
          "simpleDesc": "更多的E.G.O饰品选项"
        }
      ]
    }
  ]
}