{
  "dataList": [
    {
      "id": 0,
      "place": "评审场内部 1层",
      "model": "사회자",
      "content": "……因此，第二轮评审的最终排名将作为家主评审的最终结果。也就是说！当前评审中获得第一名的候选人……"
    },
    {
      "id": 1,
      "model": "사회자",
      "content": "将会成为下一位——荣耀的！受人尊敬的！鸿园的家主！"
    },
    {
      "id": 2,
      "model": "사회자",
      "content": "啊！就在刚才，我收到了消息，所有候选人已经平安抵达各自的起点位置！"
    },
    {
      "id": 3,
      "model": "사회자",
      "content": "现在，你们准备好开始第二轮评审了吗！"
    },
    {
      "id": 4,
      "model": "돈키호테",
      "content": "是！！！！！"
    },
    {
      "id": 5,
      "content": "……堂吉诃德是唯一一位给出了热情回应的人。"
    },
    {
      "id": 6,
      "model": "돈키호테",
      "content": "咳咳……现在，吾等该如何行事？"
    },
    {
      "id": 7,
      "model": "히스클리프",
      "content": "看到谁就先揍谁，还能干嘛？毕竟她说的是必须动用武力的战斗啊……"
    },
    {
      "id": 8,
      "model": "사회자",
      "content": "哎呀~"
    },
    {
      "id": 9,
      "model": "사회자",
      "content": "我的话还没说完，就已经看到有几位急性子的候选人迫不及待地冲出去了呢！"
    },
    {
      "id": 10,
      "model": "사회자",
      "content": "不过，在这种情况下，先听完全部的规则不是更好吗？"
    },
    {
      "id": 11,
      "model": "이스마엘",
      "content": "……听见她的话了吧。"
    },
    {
      "id": 12,
      "model": "사회자",
      "content": "各位候选人，请检查各自进来时的入口附近，那里应有一条串着铜钱的绳索。"
    },
    {
      "id": 13,
      "model": "돈키호테",
      "content": "哦……想必这便是其所言之物了！"
    },
    {
      "id": 14,
      "model": "돈키호테",
      "content": "唔，这些圆形之物是……？"
    },
    {
      "id": 15,
      "model": "로쟈",
      "content": "钱……是钱吧。是这里特有的货币吗！还发出了叮叮当当的声音。"
    },
    {
      "id": 16,
      "model": "이스마엘",
      "content": "不是……刚才主持人不是说了让我们听她说完吗？"
    },
    {
      "id": 17,
      "model": "사회자",
      "content": "现在开始，请各位珍惜并守护好那些铜钱！因为啊~"
    },
    {
      "id": 18,
      "model": "사회자",
      "content": "那正是各位候选人的生命之价值哦！"
    },
    {
      "id": 19,
      "model": "돈키호테",
      "content": "哇啊……快……快快收好！鸿璐，这可是汝生命之价值！"
    },
    {
      "id": 20,
      "content": "堂吉诃德脸色煞白，慌忙将那捆铜钱递还给鸿璐，然而希斯克利夫漫不经心地一把抓了过去。"
    },
    {
      "id": 21,
      "model": "히스클리프",
      "content": "让我看看……嗯，模样像是铜钱，但并不是真正的钱啊。这东西怎么就成了生命之价值了？"
    },
    {
      "id": 22,
      "model": "사회자",
      "content": "现在诸位大概正在纳闷，这东西为什么会是生命之价值吧！"
    },
    {
      "id": 23,
      "model": "사회자",
      "content": "那么，第二轮家主评审的规则如下。"
    },
    {
      "id": 24,
      "model": "사회자",
      "content": "所有候选人必须将铜钱串在绳子上，并挂在腰间。"
    },
    {
      "id": 25,
      "model": "사회자",
      "content": "藏在看不见的地方、吞入肚中、抑或是只携带一部分……只要没有全部挂在腰间、无法让他人清楚看见，就一律判为失格！"
    },
    {
      "id": 26,
      "model": "오티스",
      "content": "判为失格，也就是说……"
    },
    {
      "id": 27,
      "model": "히스클리프",
      "content": "喂！磨蹭什么呢，还不快拿去绑上！"
    },
    {
      "id": 28,
      "model": "싱클레어",
      "content": "不是希斯克利夫先生自己拿去的吗……？"
    },
    {
      "id": 29,
      "model": "사회자",
      "content": "所有候选人将各自获得三枚铜钱。那些将三枚铜钱全部遗失，或被他人夺走的候选人，将会被立刻淘汰！"
    },
    {
      "id": 30,
      "model": "돈키호테",
      "content": "以、以实玛利！！！那、那个，叫什么来着，绝望结对吧！请用那个绑紧，千万别让它松了啊！"
    },
    {
      "id": 31,
      "model": "이스마엘",
      "content": "我已经在这么做了……"
    },
    {
      "id": 32,
      "model": "홍루",
      "content": "啊哈哈，没必要这么着急嘛~"
    },
    {
      "id": 33,
      "model": "사회자",
      "content": "本次第二轮家主评审的时间限制为两小时，而排名……则将根据每位候选人所持有的铜钱数量来决定！"
    },
    {
      "id": 34,
      "model": "홍루",
      "content": "啊~原来这样挂上就可以了啊。"
    },
    {
      "id": 35,
      "model": "오티스",
      "content": "喂！别乱碰，给我慎重点对待！"
    },
    {
      "id": 36,
      "model": "이스마엘",
      "content": "别担心，一般情况下是掉不了的。只要没有狠狠地砍这绳子，就连割断它都很难。"
    },
    {
      "id": 37,
      "content": "此时，鸿璐的腰间已经挂上了用绳子串好的三枚铜钱。"
    },
    {
      "id": 38,
      "content": "然后，就在这一切准备就绪的那个瞬间……"
    },
    {
      "id": 39,
      "model": "사회자",
      "content": "那么，第二轮家主评审现在开始！"
    },
    {
      "id": 40,
      "content": "限时两小时的第二轮对决，正式拉开了帷幕。"
    }
  ]
}